pylak/__init__.py
pylak/animation.py
pylak/asset.py
pylak/camera.py
pylak/collider.py
pylak/engine.py
pylak/fileloader.py
pylak/physics.py
pylak/player.py
pylak/refs.py
pylak/tile.py
pylak/visual.py
pylak/game/__init__.py
pylak/game/adventure.py
pylak/resources/__init__.py
pylak-0.0.9.dist-info/LICENSE
pylak-0.0.9.dist-info/METADATA
pylak-0.0.9.dist-info/WHEEL
pylak-0.0.9.dist-info/top_level.txt
pylak-0.0.9.dist-info/RECORD
