Metadata-Version: 2.2
Name: pylak
Version: 0.0.9
Summary: Small library to learn to create 2D games
Author-email: Valter Yde Daugberg <valteryde@hotmail.com>
Project-URL: Homepage, https://github.com/valteryde/pylak
Project-URL: Issues, https://github.com/valteryde/kaxe/pylak
Classifier: Programming Language :: Python :: 3
Classifier: License :: OSI Approved :: GNU General Public License v3 (GPLv3)
Classifier: Operating System :: OS Independent
Requires-Python: >=3.9
License-File: LICENSE
Requires-Dist: numpy
Requires-Dist: pygame
Requires-Dist: pymunk
Requires-Dist: pillow
